TicTacCode/Board.py
TicTacCode/__init__.py
TicTacCode-0.1.2.dist-info/LICENSE.txt
TicTacCode-0.1.2.dist-info/METADATA
TicTacCode-0.1.2.dist-info/WHEEL
TicTacCode-0.1.2.dist-info/top_level.txt
TicTacCode-0.1.2.dist-info/RECORD
