Metadata-Version: 2.1
Name: TicTacCode
Version: 0.1.2
Summary: Python Tic-Tac-Toe Library.
Author: Amos Xiao
Author-email: AmosXiao1000020@proton.me
Requires-Python: >=3.10
License-File: LICENSE.txt
